[{"word":"công ăn việc làm","definitions":[{"dicts":["Từ điển Tiếng Việt thông dụng"],"text":"việc làm để sinh sống [nói khái quát]\nVí dụ:\n- không có công ăn việc làm ổn định","type":"mono"},{"dicts":["VNEDICT"],"text":"job, position, work, situation, employment","type":"bilingual"},{"dicts":["Babylon"],"text":"[công ăn việc làm] work; job; situation; employment \n Kế hoạch tạo công ăn việc làm \n Job creation scheme \n Sự bảo đảm công ăn việc làm ổn định \n Security of employment; job security \n Tạo công ăn việc làm cho những người tự nguyện hồi hương \n To create jobs for voluntary repatriates; \n To give employment to voluntary repatriates","type":"bilingual"}]}]