[{"word":"gié","definitions":[{"dicts":["Việt Anh - Hồ Ngọc Đức"],"text":"@gié\n- Rice-ear","type":"bilingual"},{"dicts":["Từ điển Tiếng Việt thông dụng"],"text":"nhánh của cụm hoa kiểu bông kép\nVí dụ:\n- gié lúa \n - trừ sâu cắn gié","type":"mono"},{"dicts":["VNEDICT"],"text":"rice-ear","type":"bilingual"},{"dicts":["Babylon"],"text":"[gié] \n Rice-ear.","type":"bilingual"},{"dicts":["Từ điển Tiếng Việt - Hồ Ngọc Đức"],"text":"@Gié\n- (Dgieh, Tareh) Tên gọi một nhóm nhỏ của dân tộc Gia-rai","type":"mono"},{"dicts":["Từ điển Tiếng Việt - Hồ Ngọc Đức"],"text":"@gié\n- d. Bông lúa: Sâu cắn gié.","type":"mono"}]},{"word":"gié đá","definitions":[{"dicts":["Babylon"],"text":"[gié đá] a variety of rice","type":"bilingual"}]},{"word":"giéo giắt","definitions":[{"dicts":["Việt Anh - Hồ Ngọc Đức"],"text":"@giéo giắt\n- Melodious\n=Tiếng sáo giéo giắc+The melodious notes of a flute","type":"bilingual"},{"dicts":["Babylon"],"text":"[giéo giắt] \n Melodious. Tiếng sáo giéo giắc \n The melodious notes of a flute.","type":"bilingual"},{"dicts":["Từ điển Tiếng Việt - Hồ Ngọc Đức"],"text":"@giéo giắt\n- t. Nói những tiếng véo von thánh thót do sự hòa hợp các âm thanh gây nên: Khúc đàn giéo giắt.","type":"mono"}]},{"word":"gié hoa","definitions":[{"dicts":["Babylon"],"text":"[gié hoa] spikelet","type":"bilingual"}]}]