[{"word":"thõng","definitions":[{"dicts":["Từ điển Tiếng Việt thông dụng"],"text":"để cho buông thẳng xuống một cách tự nhiên\nVí dụ:\n- quả mướp thõng xuống giàn \n - nó thõng chân xuống ghế","type":"mono"},{"dicts":["Babylon"],"text":"tính từ hanging, danging, waving anh ta bước đi, đôi tay thõng xuống (hai bên) he walks with his arms dangling(his arm loosely by his sides) elongated earthen vase","type":"bilingual"},{"dicts":["Từ điển Tiếng Việt - Hồ Ngọc Đức"],"text":"@thõng\n- t. Bỏ xuống không dựa vào đâu: Ngồi trên cây thõng chân.\n- d. Thứ vò nhỏ và dài.","type":"mono"}]},{"word":"thõng thẹo","definitions":[{"dicts":["Từ điển Tiếng Việt thông dụng"],"text":"ở trạng thái buông thõng xuống và đung đưa một cách yếu ớt\nVí dụ:\n- đi đứng thõng thẹo","type":"mono"},{"dicts":["Babylon"],"text":"tính từ languid, listless slack, inert, nerveless","type":"bilingual"},{"dicts":["Từ điển Tiếng Việt - Hồ Ngọc Đức"],"text":"@thõng thẹo\n- Mềm yếu và chậm chạp: Đi thõng thẹo.","type":"mono"}]},{"word":"thõng thượt","definitions":[{"dicts":["Từ điển Tiếng Việt thông dụng"],"text":"từ gợi tả dáng vẻ dài thượt ra và buông thõng xuống\nVí dụ:\n- nằm thõng thượt trên giường","type":"mono"}]}]