[{"word":"thỗn thện","definitions":[{"dicts":["Từ điển Tiếng Việt thông dụng"],"text":"[bộ ngực người phụ nữ] quá to và để hở hang, bày ra một cách lộ liễu, trông khó coi\nVí dụ:\n- vú vê thỗn thện","type":"mono"},{"dicts":["Babylon"],"text":"như thỗn thễn","type":"bilingual"},{"dicts":["Từ điển Tiếng Việt - Hồ Ngọc Đức"],"text":"@thỗn thện\n- Nói phụ nữ để phơi lộ bộ ngực nở.","type":"mono"}]},{"word":"thỗn thễn","definitions":[{"dicts":["Babylon"],"text":"phó từ naked, nude, unclothed","type":"bilingual"}]}]