[{"word":"trĩu trịt","definitions":[{"dicts":["Từ điển Tiếng Việt thông dụng"],"text":"quá nhiều, làm cho trĩu xuống\nVí dụ:\n- cành cây trĩu trịt quả","type":"mono"},{"dicts":["Từ điển Tiếng Việt - Hồ Ngọc Đức"],"text":"@trĩu trịt\n- Nh. Trĩu: Gánh gạo trĩu trịt.","type":"mono"}]},{"word":"trĩ sang","definitions":[{"dicts":["VNEDICT"],"text":"hemorrhoid","type":"bilingual"},{"dicts":["Babylon"],"text":"[trĩ sang] haemorrhoids, piles","type":"bilingual"}]},{"word":"trĩ","definitions":[{"dicts":["Từ điển Tiếng Việt thông dụng"],"text":"chim cùng họ với gà, sống ở rừng, con trống có bộ lông đẹp, đuôi dài\nVí dụ:\n- chim trĩ","type":"mono"},{"dicts":["Từ điển Tiếng Việt thông dụng"],"text":"bệnh dãn tĩnh mạch hậu môn, thường sinh ra chứng đi ngoài ra máu\nVí dụ:\n- mắc bệnh trĩ \n - cắt trĩ","type":"mono"},{"dicts":["VNEDICT"],"text":"(1) pheasant; (2) infant; (3) hemorrhoid","type":"bilingual"},{"dicts":["Babylon"],"text":"[trĩ] xem bệnh trĩ","type":"bilingual"},{"dicts":["Từ điển Tiếng Việt - Hồ Ngọc Đức"],"text":"@trĩ\n- d. Bệnh phình tĩnh mạch hậu môn, sinh ra chứng đi ngoài ra máu.","type":"mono"}]},{"word":"trĩu","definitions":[{"dicts":["Từ điển Tiếng Việt thông dụng"],"text":"bị sa thấp hoặc cong oằn hẳn xuống do sức nặng\nVí dụ:\n- lúa trĩu bông \n - cây sai trĩu quả \n - gánh nặng, trĩu cả vai","type":"mono"},{"dicts":["VNEDICT"],"text":"laden, heavy","type":"bilingual"},{"dicts":["Babylon"],"text":"[trĩu] laden; heavy \n Cây trĩu quả \n A tree laden/heavy with fruit; a tree weighed down with fruit \n Lòng trĩu nặng ưu sầu \n To be weighed down with grief/sorrow","type":"bilingual"},{"dicts":["Từ điển Tiếng Việt - Hồ Ngọc Đức"],"text":"@trĩu\n- ph, t. Cg. Trĩu trịt. Sa xuống vì nặng quá: Cành cam trĩu những quả; Gánh lúa nặng trĩu.","type":"mono"}]},{"word":"trĩ lập","definitions":[{"dicts":["Babylon"],"text":"[trĩ lập] stand (like a mountain)","type":"bilingual"}]},{"word":"trĩ cam","definitions":[{"dicts":["Babylon"],"text":"[trĩ cam] septicemia","type":"bilingual"}]},{"word":"trĩu nặng","definitions":[{"dicts":["Từ điển Tiếng Việt thông dụng"],"text":"như nặng trĩu\nVí dụ:\n- mí mắt trĩu nặng \n - lòng trĩu nặng lo âu","type":"mono"}]},{"word":"trĩ chứng","definitions":[{"dicts":["Babylon"],"text":"[trĩ chứng] hemorrhoids, have piles","type":"bilingual"}]},{"word":"trĩ sao","definitions":[{"dicts":["VNEDICT"],"text":"pheinardia ocellata","type":"bilingual"},{"dicts":["Babylon"],"text":"[trĩ sao] pheinardia ocellata","type":"bilingual"}]},{"word":"trĩ mũi","definitions":[{"dicts":["Từ điển Tiếng Việt thông dụng"],"text":"bệnh viêm, teo và thối niêm mạc mũi","type":"mono"},{"dicts":["VNEDICT"],"text":"polypus in the nose","type":"bilingual"},{"dicts":["Babylon"],"text":"[trĩ mũi] polypus in the nose","type":"bilingual"},{"dicts":["Từ điển Tiếng Việt - Hồ Ngọc Đức"],"text":"@trĩ mũi\n- Từ chỉ chung những bệnh viêm mũi hay thối mũi.","type":"mono"}]}]