[{"word":"tát","definitions":[{"dicts":["Việt Anh - Hồ Ngọc Đức"],"text":"@tát\n* verb\n- to slap. to scoop (water). to bail out of (a boat)","type":"bilingual"},{"dicts":["Từ điển Tiếng Việt thông dụng"],"text":"đánh mạnh vào mặt bằng bàn tay đang mở\nVí dụ:\n- lão tát nó mấy cái vào mặt \n - tát thẳng tay","type":"mono"},{"dicts":["Từ điển Tiếng Việt thông dụng"],"text":"cái đánh vào mặt bằng bàn tay đang mở\nVí dụ:\n- cho nó mấy cái tát","type":"mono"},{"dicts":["Từ điển Tiếng Việt thông dụng"],"text":"dùng gàu hoặc xô, chậu, v.v. để chuyển nước từ nơi này sang nơi khác, thường bằng động tác hất mạnh\nVí dụ:\n- tát ao bắt cá \n - bố tôi đang tát ao","type":"mono"},{"dicts":["VNEDICT"],"text":"to slap, hit; to scoop (water), bail out (a boat)","type":"bilingual"},{"dicts":["Babylon"],"text":"[tát] xem bạt tai xem tát nước xem tát cạn","type":"bilingual"},{"dicts":["Từ điển Tiếng Việt - Hồ Ngọc Đức"],"text":"@tát\n- 1 đg. (hoặc d.). Đánh vào mặt bằng bàn tay mở. Tát đánh bốp vào mặt. Cho mấy cái tát. Tát tai*.\n- 2 đg. Đưa chuyển bớt nước từ nơi nọ sang nơi kia, thường bằng gàu. Tát nước chống hạn. Tát ao bắt cá. Mắng như tát nước (vào mặt).","type":"mono"}]},{"word":"tát cạn","definitions":[{"dicts":["Babylon"],"text":"[tát cạn] to dry up","type":"bilingual"}]},{"word":"Tát Ngà","definitions":[{"dicts":["Từ điển Tiếng Việt - Hồ Ngọc Đức"],"text":"@Tát Ngà\n- (xã) h. Mèo Vạc, t. Hà Giang","type":"mono"}]},{"word":"tát tai","definitions":[{"dicts":["Từ điển Tiếng Việt thông dụng"],"text":"như bạt tai\nVí dụ:\n- ông tát tai thằng bé một cái rõ đau","type":"mono"},{"dicts":["VNEDICT"],"text":"to hit, slap, box","type":"bilingual"},{"dicts":["Babylon"],"text":"[tát tai] xem bạt tai","type":"bilingual"},{"dicts":["Từ điển Tiếng Việt - Hồ Ngọc Đức"],"text":"@tát tai\n- Cg. Tạt tai. Tát vào phía sau vành tai.","type":"mono"}]},{"word":"tát trái","definitions":[{"dicts":["Từ điển Tiếng Việt - Hồ Ngọc Đức"],"text":"@tát trái\n- Tát bằng mu bàn tay.","type":"mono"}]},{"word":"tát nước","definitions":[{"dicts":["Babylon"],"text":"[tát nước] to bail out water \n Tát nước trong thuyền ra \n To bail out the boat","type":"bilingual"}]}]