[{"word":"ừ nhỉ","definitions":[{"dicts":["VNEDICT"],"text":"okay, yes","type":"bilingual"}]},{"word":"ừ","definitions":[{"dicts":["Từ điển Tiếng Việt thông dụng"],"text":"tiếng dùng để trả lời người ngang hàng hoặc người dưới, tỏ sự đồng ý, nhất trí\nVí dụ:\n- (- trời mưa à?) - ừ! \n - ừ nhỉ, thế mà tôi quên khuấy đi mất!","type":"mono"},{"dicts":["Từ điển Tiếng Việt thông dụng"],"text":"tỏ sự đồng ý\nVí dụ:\n- quan tám cũng ừ, quan tư cũng gật (tng)","type":"mono"},{"dicts":["VNEDICT"],"text":"to consent; yes","type":"bilingual"},{"dicts":["Babylon"],"text":"yes (familiar), all right, \n O. K.","type":"bilingual"}]},{"word":"ừ è","definitions":[{"dicts":["VNEDICT"],"text":"to give an evasive answer","type":"bilingual"}]},{"word":"ừ nhé","definitions":[{"dicts":["Babylon"],"text":"you agree, don't you ?","type":"bilingual"}]},{"word":"ừ ừ ào ào","definitions":[{"dicts":["VNEDICT","Babylon"],"text":"say yes to everything and do nothing","type":"bilingual"}]},{"word":"ừ ầm","definitions":[{"dicts":["Babylon"],"text":"như ừ ào","type":"bilingual"}]},{"word":"ừ ào","definitions":[{"dicts":["Từ điển Tiếng Việt thông dụng"],"text":"ừ đại đi cho qua chuyện, không để ý lắm\nVí dụ:\n- hỏi gì cũng chỉ ừ ào","type":"mono"},{"dicts":["VNEDICT","Babylon"],"text":"say \"yes\" and not mean it","type":"bilingual"}]},{"word":"ừ thì","definitions":[{"dicts":["Babylon"],"text":"well, \n I agree","type":"bilingual"}]},{"word":"ừ hữ","definitions":[{"dicts":["Từ điển Tiếng Việt thông dụng"],"text":"trả lời không rõ ràng, không ra đồng ý cũng không ra từ chối\nVí dụ:\n- ừ hữ cho qua chuyện","type":"mono"},{"dicts":["VNEDICT","Babylon"],"text":"answer evasively","type":"bilingual"}]},{"word":"ừ ừ","definitions":[{"dicts":["Babylon"],"text":"yes, yes","type":"bilingual"}]},{"word":"ừng ực","definitions":[{"dicts":["Từ điển Tiếng Việt thông dụng"],"text":"từ mô phỏng tiếng nuốt chất lỏng mạnh và liên tiếp từng hơi dài\nVí dụ:\n- tu nước ừng ực","type":"mono"},{"dicts":["VNEDICT"],"text":"gulp down, swallow","type":"bilingual"},{"dicts":["Babylon"],"text":"động từ gulp down, swallow","type":"bilingual"}]}]